python_sts_payone/__init__.py
python_sts_payone/base/__init__.py
python_sts_payone/base/request_handler.py
python_sts_payone/base/utils.py
python_sts_payone/redirection_model/__init__.py
python_sts_payone/redirection_model/redirect_payment.py
python_sts_payone/secure_hash/__init__.py
python_sts_payone/secure_hash/secure_hash_generator.py
python_sts_payone/supporting/__init__.py
python_sts_payone/supporting/inquiry.py
python_sts_payone-0.1.2.dist-info/METADATA
python_sts_payone-0.1.2.dist-info/WHEEL
python_sts_payone-0.1.2.dist-info/licenses/LICENSE
python_sts_payone-0.1.2.dist-info/RECORD
